sj_rando/__init__.py
sj_rando/infos.py
sj_rando/items.py
sj_rando/main.py
sj_rando/randomizer.py
sj_rando/subrando.py
sj_rando-0.1.2.dist-info/METADATA
sj_rando-0.1.2.dist-info/WHEEL
sj_rando-0.1.2.dist-info/entry_points.txt
sj_rando-0.1.2.dist-info/RECORD
