Metadata-Version: 2.3
Name: sj_rando
Version: 0.1.2
Summary: A tool to randomize a Solar Jetman (NES) rom file.
Project-URL: Repository, https://github.com/akerasi/SJ-rando
Project-URL: Issues, https://github.com/akerasi/SJ-rando/issues
Author: Niamek
Author-email: akerasi <akerasi@gmail.com>
License: MIT License
Keywords: NES,Solar Jetman,famicom,nes,randomizer,retro
Requires-Python: >=3.8
